jst_django/cli/app.py
jst_django/cli/main.py
jst_django/commands/__init__.py
jst_django/commands/aic.py
jst_django/commands/create.py
jst_django/commands/generate.py
jst_django/commands/init.py
jst_django/commands/install.py
jst_django/commands/requirements.py
jst_django/commands/translate.py
jst_django/stubs/__init__.stub
jst_django/stubs/admin.stub
jst_django/stubs/django/admin.stub
jst_django/stubs/django/model.stub
jst_django/stubs/django/serializer.stub
jst_django/stubs/filter.stub
jst_django/stubs/form.stub
jst_django/stubs/model.stub
jst_django/stubs/permission.stub
jst_django/stubs/requirements.txt.stub
jst_django/stubs/serializer.stub
jst_django/stubs/signal.stub
jst_django/stubs/test.stub
jst_django/stubs/translation.stub
jst_django/stubs/validator.stub
jst_django/stubs/view.stub
jst_django/utils/__init__.py
jst_django/utils/api.py
jst_django/utils/ast_utils.py
jst_django/utils/base.py
jst_django/utils/code.py
jst_django/utils/file.py
jst_django/utils/logger.py
jst_django/utils/progress.py
jst_django/utils/tokenize.py
jst_django-4.4.5.dist-info/METADATA
jst_django-4.4.5.dist-info/WHEEL
jst_django-4.4.5.dist-info/entry_points.txt
jst_django-4.4.5.dist-info/RECORD
