Metadata-Version: 2.4
Name: jst-django
Version: 4.4.5
Summary: 
Author: A'zamov Samandar
Author-email: JscorpTech@gmail.com
Requires-Python: >=3.9,<4.0
Classifier: Programming Language :: Python :: 3
Classifier: Programming Language :: Python :: 3.9
Classifier: Programming Language :: Python :: 3.10
Classifier: Programming Language :: Python :: 3.11
Classifier: Programming Language :: Python :: 3.12
Classifier: Programming Language :: Python :: 3.13
Classifier: Programming Language :: Python :: 3.14
Requires-Dist: arrow (==1.3.0)
Requires-Dist: astor (>=0.8.1,<0.9.0)
Requires-Dist: binaryornot (==0.4.4)
Requires-Dist: black (==24.10.0)
Requires-Dist: certifi (==2024.8.30)
Requires-Dist: chardet (==5.2.0)
Requires-Dist: charset-normalizer (==3.4.0)
Requires-Dist: click (==8.1.7)
Requires-Dist: colorlog (>=6.9.0,<7.0.0)
Requires-Dist: cookiecutter (==2.6.0)
Requires-Dist: idna (==3.10)
Requires-Dist: isort (>=5.13.2,<6.0.0)
Requires-Dist: jinja2 (==3.1.4)
Requires-Dist: jst-aicommit (>=1.2,<2.0)
Requires-Dist: markdown-it-py (==3.0.0)
Requires-Dist: markupsafe (==3.0.2)
Requires-Dist: mdurl (==0.1.2)
Requires-Dist: mypy-extensions (==1.0.0)
Requires-Dist: packaging (==24.1)
Requires-Dist: pathspec (==0.12.1)
Requires-Dist: platformdirs (==4.3.6)
Requires-Dist: polib (>=1.2.0,<2.0.0)
Requires-Dist: pygments (==2.18.0)
Requires-Dist: python-dateutil (==2.9.0.post0)
Requires-Dist: python-slugify (==8.0.4)
Requires-Dist: pyyaml (==6.0.2)
Requires-Dist: questionary (==2.0.1)
Requires-Dist: requests (==2.32.3)
Requires-Dist: rich (==13.9.3)
Requires-Dist: shellingham (==1.5.4)
Requires-Dist: six (==1.16.0)
Requires-Dist: text-unidecode (==1.3)
Requires-Dist: tqdm (>=4.67.0,<5.0.0)
Requires-Dist: typer (==0.12.5)
Requires-Dist: types-python-dateutil (==2.9.0.20241003)
Requires-Dist: typing-extensions (==4.12.2)
Requires-Dist: urllib3 (==2.2.3)
Requires-Dist: wcwidth (==0.2.13)
Requires-Dist: zipfile36 (==0.1.3)
